CHANGES.rst
LICENSE.txt
MANIFEST.in
README.rst
setup.py
exr/__init__.py
exr/meta_builder.py
exr/builder/__init__.py
exr/builder/_exrb.py
exr/builder/common.py
exr_builder.egg-info/PKG-INFO
exr_builder.egg-info/SOURCES.txt
exr_builder.egg-info/dependency_links.txt
exr_builder.egg-info/entry_points.txt
exr_builder.egg-info/requires.txt
exr_builder.egg-info/top_level.txt