Metadata-Version: 1.1
Name: exr-builder
Version: 0.1.7
Summary: Lightweight Python Build Tool.
Home-page: https://code.exrny.com/opensource/exr-builder/
Author: Peter Salnikov
Author-email: opensource@exrny.com
License: MIT License
Keywords: devops,build tool
Platform: UNKNOWN
Classifier: Development Status :: 4 - Beta
Classifier: Environment :: Console
Classifier: Intended Audience :: System Administrators
Classifier: Intended Audience :: Developers
Classifier: License :: OSI Approved :: MIT License
Classifier: Programming Language :: Python :: 2
Classifier: Programming Language :: Python :: 3
Classifier: Topic :: Software Development :: Build Tools
